ember_csi/__init__.py
ember_csi/base.py
ember_csi/capabilities.py
ember_csi/cl_crd.py
ember_csi/common.py
ember_csi/config.py
ember_csi/constants.py
ember_csi/defaults.py
ember_csi/ember_csi.py
ember_csi/generate_drivers_map.py
ember_csi/liveness.py
ember_csi/messages.py
ember_csi/rpdb.py
ember_csi/workarounds.py
ember_csi/v0_2_0/__init__.py
ember_csi/v0_2_0/csi.py
ember_csi/v0_2_0/csi_pb2.py
ember_csi/v0_2_0/csi_pb2_grpc.py
ember_csi/v0_2_0/csi_types.py
ember_csi/v0_3_0/__init__.py
ember_csi/v0_3_0/csi.py
ember_csi/v0_3_0/csi_pb2.py
ember_csi/v0_3_0/csi_pb2_grpc.py
ember_csi/v0_3_0/csi_types.py
ember_csi/v1_0_0/__init__.py
ember_csi/v1_0_0/csi.py
ember_csi/v1_0_0/csi_base.py
ember_csi/v1_0_0/csi_pb2.py
ember_csi/v1_0_0/csi_pb2_grpc.py
ember_csi/v1_0_0/csi_types.py
ember_csi/v1_1_0/__init__.py
ember_csi/v1_1_0/csi.py
ember_csi/v1_1_0/csi_pb2.py
ember_csi/v1_1_0/csi_pb2_grpc.py
ember_csi/v1_1_0/csi_types.py
ember_csi-0.9.1.data/data/HISTORY.md
ember_csi-0.9.1.data/data/README.md
ember_csi-0.9.1.data/data/patches/apply-patches
ember_csi-0.9.1.dist-info/AUTHORS.rst
ember_csi-0.9.1.dist-info/LICENSE
ember_csi-0.9.1.dist-info/METADATA
ember_csi-0.9.1.dist-info/WHEEL
ember_csi-0.9.1.dist-info/entry_points.txt
ember_csi-0.9.1.dist-info/top_level.txt
ember_csi-0.9.1.dist-info/zip-safe
ember_csi-0.9.1.dist-info/RECORD
