Metadata-Version: 2.1
Name: ember-csi
Version: 0.9.1
Summary: Multi-vendor CSI plugin supporting over 80 storage drivers
Home-page: https://github.com/akrog/ember-csi
Author: Gorka Eguileor
Author-email: gorka@eguileor.com
License: Apache Software License 2.0
Keywords: ember_csi
Platform: UNKNOWN
Classifier: Development Status :: 4 - Beta
Classifier: Intended Audience :: Developers
Classifier: Intended Audience :: Information Technology
Classifier: License :: OSI Approved :: Apache Software License
Classifier: Natural Language :: English
Classifier: Programming Language :: Python :: 3
Classifier: Programming Language :: Python :: 3.6
Requires-Dist: cinderlib (>=0.9.0)
Requires-Dist: grpcio (>=1.15.0)
Requires-Dist: protobuf (>=3.5.0.post1)
Requires-Dist: kubernetes (<12.0.0,>=7.0.0)
